pycamgeom/__init__.py
pycamgeom/aabbtree.py
pycamgeom/camera.py
pycamgeom/frame.py
pycamgeom/projector.py
pycamgeom-0.0.5.dist-info/LICENSE
pycamgeom-0.0.5.dist-info/METADATA
pycamgeom-0.0.5.dist-info/WHEEL
pycamgeom-0.0.5.dist-info/top_level.txt
pycamgeom-0.0.5.dist-info/RECORD
