Metadata-Version: 2.1
Name: pycamgeom
Version: 0.0.5
Summary: 'camera models and associated classes'
Home-page: https://github.com/bmhopkinson/pycamgeom
Author: Brian Hopkinson
Author-email: bmhopkin@uga.edu
License: UNKNOWN
Platform: UNKNOWN
Classifier: Programming Language :: Python :: 3
Classifier: License :: OSI Approved :: MIT License
Requires-Python: >=3.6
License-File: LICENSE
